CHANGES.rst
LICENSE
MANIFEST.in
README.rst
setup.cfg
setup.py
seccure.egg-info/PKG-INFO
seccure.egg-info/SOURCES.txt
seccure.egg-info/dependency_links.txt
seccure.egg-info/requires.txt
seccure.egg-info/top_level.txt
seccure.egg-info/zip-safe
src/__init__.py
src/_version.py
src/tests/__init__.py
src/tests/test_ec.py
src/tests/test_helpers.py
src/tests/test_issues.py
src/tests/test_main.py