Metadata-Version: 1.1
Name: seccure
Version: 0.4.1
Summary: SECCURE compatible Elliptic Curve cryptography
Home-page: http://github.com/bwesterb/py-seccure
Author: Bas Westerbaan
Author-email: bas@westerbaan.name
License: LGPL 3.0
Platform: UNKNOWN
Classifier: Development Status :: 4 - Beta
Classifier: License :: OSI Approved :: GNU Lesser General Public License v3 (LGPLv3)
Classifier: Operating System :: POSIX
Classifier: Topic :: Security
Classifier: Programming Language :: Python :: 2.7
Classifier: Programming Language :: Python :: 3.4
Classifier: Programming Language :: Python :: 3.5
Classifier: Programming Language :: Python :: 3.6
Classifier: Programming Language :: Python :: 3.7
